anchor_stack/__init__.py
anchor_stack/cli.py
anchor_stack/server.py
anchor_stack/core/__init__.py
anchor_stack/core/config.py
anchor_stack/core/exceptions.py
anchor_stack/core/logger.py
anchor_stack/models/__init__.py
anchor_stack/models/pack.py
anchor_stack/models/project.py
anchor_stack/models/stack.py
anchor_stack/models/stack_spec.py
anchor_stack/services/__init__.py
anchor_stack/services/file_writer.py
anchor_stack/services/pack_manager.py
anchor_stack/services/rules_generator.py
anchor_stack/services/stack_manager.py
anchor_stack/services/template_renderer.py
anchor_stack/stacks/fastapi/stack.yaml
anchor_stack/stacks/fastapi/rules/claude.md.j2
anchor_stack/stacks/fastapi/rules/cursor.mdc.j2
anchor_stack/stacks/fastapi/rules/windsurf.md.j2
anchor_stack/stacks/fastapi/templates/.env.example
anchor_stack/stacks/fastapi/templates/.gitignore
anchor_stack/stacks/fastapi/templates/README.md.j2
anchor_stack/stacks/fastapi/templates/pyproject.toml.j2
anchor_stack/stacks/fastapi/templates/src/app/__init__.py.j2
anchor_stack/stacks/fastapi/templates/src/app/main.py.j2
anchor_stack/stacks/fastapi/templates/src/app/api/__init__.py
anchor_stack/stacks/fastapi/templates/src/app/api/v1/__init__.py
anchor_stack/stacks/fastapi/templates/src/app/api/v1/health.py
anchor_stack/stacks/fastapi/templates/src/app/api/v1/router.py
anchor_stack/stacks/fastapi/templates/src/app/api/v1/users.py
anchor_stack/stacks/fastapi/templates/src/app/core/__init__.py.j2
anchor_stack/stacks/fastapi/templates/src/app/core/config.py
anchor_stack/stacks/fastapi/templates/src/app/core/logger.py
anchor_stack/stacks/fastapi/templates/src/app/models/__init__.py
anchor_stack/stacks/fastapi/templates/src/app/schemas/__init__.py
anchor_stack/stacks/fastapi/templates/src/app/schemas/response.py
anchor_stack/stacks/fastapi/templates/src/app/schemas/user.py
anchor_stack/stacks/fastapi/templates/src/app/services/__init__.py
anchor_stack/stacks/fastapi/templates/tests/__init__.py
anchor_stack-0.1.3.dist-info/METADATA
anchor_stack-0.1.3.dist-info/WHEEL
anchor_stack-0.1.3.dist-info/entry_points.txt
anchor_stack-0.1.3.dist-info/licenses/LICENSE
anchor_stack-0.1.3.dist-info/RECORD
