Metadata-Version: 2.4
Name: anchor-stack
Version: 0.1.3
Summary: AI-friendly engineering foundation with stable versions, unified logging, and pluggable capability packs
Project-URL: Homepage, https://github.com/anchor-stack/anchor-stack
Project-URL: Documentation, https://github.com/anchor-stack/anchor-stack#readme
Project-URL: Repository, https://github.com/anchor-stack/anchor-stack
Project-URL: Issues, https://github.com/anchor-stack/anchor-stack/issues
Author: Anchor Stack Team
License: MIT
License-File: LICENSE
Keywords: ai,debug,engineering,mcp,scaffolding,template
Classifier: Development Status :: 3 - Alpha
Classifier: Intended Audience :: Developers
Classifier: License :: OSI Approved :: MIT License
Classifier: Programming Language :: Python :: 3
Classifier: Programming Language :: Python :: 3.10
Classifier: Programming Language :: Python :: 3.11
Classifier: Programming Language :: Python :: 3.12
Classifier: Programming Language :: Python :: 3.13
Classifier: Topic :: Software Development :: Code Generators
Classifier: Topic :: Software Development :: Libraries :: Python Modules
Requires-Python: >=3.10
Requires-Dist: click<9.0.0,>=8.3.0
Requires-Dist: jinja2<4.0.0,>=3.1.6
Requires-Dist: mcp<2.0.0,>=1.25.0
Requires-Dist: pydantic-settings<3.0.0,>=2.12.0
Requires-Dist: pydantic<3.0.0,>=2.12.0
Requires-Dist: pyyaml<7.0.0,>=6.0.3
Requires-Dist: typing-extensions>=4.12.0
Provides-Extra: dev
Requires-Dist: mypy>=1.14.0; extra == 'dev'
Requires-Dist: pre-commit>=4.0.0; extra == 'dev'
Requires-Dist: pytest-asyncio>=0.24.0; extra == 'dev'
Requires-Dist: pytest-cov>=6.0.0; extra == 'dev'
Requires-Dist: pytest>=8.0.0; extra == 'dev'
Requires-Dist: ruff>=0.9.0; extra == 'dev'
